stepshifter3/__init__.py
stepshifter3/callbacks.py
stepshifter3/generatereport.py
stepshifter3/stepshifter.py
stepshifter3/synthetic_data_generator.py
stepshifter3-0.0.1.dist-info/LICENSE
stepshifter3-0.0.1.dist-info/METADATA
stepshifter3-0.0.1.dist-info/WHEEL
stepshifter3-0.0.1.dist-info/top_level.txt
stepshifter3-0.0.1.dist-info/RECORD
