Metadata-Version: 2.1
Name: stepshifter3
Version: 0.0.1
Summary: A general purpose stepshifting algorithm for tabular data, based on BaseEstimator.
Home-page: https://www.github.com/prio-data/stepshifter3
Author: Tom Daniel Grande
Author-email: tomdgrande@gmail.com
License: MIT
License-File: LICENSE
Requires-Dist: geopandas >=0.13.2
Requires-Dist: ingester3 ==1.9.1
Requires-Dist: joblib ==1.3.2
Requires-Dist: lightgbm ==4.0.0
Requires-Dist: matplotlib >=3.7.0
Requires-Dist: mlflow >=2.6.0
Requires-Dist: numpy ==1.25.0
Requires-Dist: pandas ==1.5.2
Requires-Dist: seaborn ==0.12.2
Requires-Dist: scikit-learn >=1.3.0
Requires-Dist: sqlalchemy ==1.4.49
Requires-Dist: views-mapper2
Requires-Dist: xgboost ==1.7.6
Requires-Dist: viewser ==6.0.0
Requires-Dist: tqdm ==4.66.1
